ser_Anton
