Metadata-Version: 2.1
Name: ser-Galuts
Version: 0.1.2
Summary: somme serialization
Home-page: UNKNOWN
Author: Galuts Anton
Author-email: lil_evac@mail.ru
License: MIT
Platform: UNKNOWN
Classifier: Intended Audience :: Developers
Classifier: License :: OSI Approved :: MIT License
Classifier: Programming Language :: Python :: 3.10
Classifier: Operating System :: OS Independent
